powerlawrs-0.0.15.dist-info/METADATA
powerlawrs-0.0.15.dist-info/WHEEL
powerlawrs-0.0.15.dist-info/licenses/LICENSE-APACHE
powerlawrs-0.0.15.dist-info/licenses/LICENSE-MIT
powerlawrs/__init__.py
powerlawrs/_powerlawrs.cpython-313-powerpc64le-linux-gnu.so
powerlawrs-0.0.15.dist-info/RECORD
